instld/__init__.py
instld/errors.py
instld/cli/__init__.py
instld/cli/main.py
instld/cli/parsing_arguments/__init__.py
instld/cli/parsing_arguments/get_python_file.py
instld/cli/parsing_comments/__init__.py
instld/cli/parsing_comments/get_comment_string.py
instld/cli/parsing_comments/get_options_from_comments.py
instld/cli/traceback_cutting/__init__.py
instld/cli/traceback_cutting/cutting.py
instld/cli/traceback_cutting/traceback_utils.py
instld/common_utils/__init__.py
instld/common_utils/convert_options.py
instld/module/__init__.py
instld/module/command_executer.py
instld/module/context.py
instld/module/context_manager.py
instld/module/empty_logger.py
instld/module/lock.py
instld/module/proxy_module.py
instld/module/runner.py
instld/state_management/__init__.py
instld/state_management/storage.py
instld-0.0.25.dist-info/LICENSE
instld-0.0.25.dist-info/METADATA
instld-0.0.25.dist-info/WHEEL
instld-0.0.25.dist-info/entry_points.txt
instld-0.0.25.dist-info/top_level.txt
instld-0.0.25.dist-info/RECORD
