Metadata-Version: 2.1
Name: instld
Version: 0.0.25
Summary: The simplest package management
Author-email: Evgeniy Blinov <zheni-b@yandex.ru>
Project-URL: Source, https://github.com/pomponchik/instld
Project-URL: Tracker, https://github.com/pomponchik/instld/issues
Classifier: Operating System :: MacOS :: MacOS X
Classifier: Operating System :: Microsoft :: Windows
Classifier: Operating System :: POSIX
Classifier: Programming Language :: Python :: 3.7
Classifier: Programming Language :: Python :: 3.8
Classifier: Programming Language :: Python :: 3.9
Classifier: Programming Language :: Python :: 3.10
Classifier: Programming Language :: Python :: 3.11
Classifier: Programming Language :: Python :: 3.12
Classifier: License :: OSI Approved :: MIT License
Classifier: Topic :: Software Development :: Libraries
Classifier: Topic :: Software Development :: Interpreters
Classifier: Topic :: Utilities
Classifier: Topic :: System :: Archiving :: Packaging
Classifier: Intended Audience :: System Administrators
Classifier: Intended Audience :: Developers
Requires-Python: >=3.7
License-File: LICENSE
